aioelschools/__init__.py
aioelschools/categories.py
aioelschools/api/__init__.py
aioelschools/api/api.py
aioelschools/errors/__init__.py
aioelschools/errors/errors.py
aioelschools/methods/__init__.py
aioelschools/methods/basemodel.py
aioelschools/methods/chart.py
aioelschools/methods/department.py
aioelschools/methods/dictionary.py
aioelschools/methods/login.py
aioelschools/methods/user.py
aioelschools/models/__init__.py
aioelschools/models/models.py
aioelschools/utils/__init__.py
aioelschools/utils/code_exception.py
aioelschools/utils/response_processor.py
aioelschools-1.0.6.dist-info/METADATA
aioelschools-1.0.6.dist-info/WHEEL
aioelschools-1.0.6.dist-info/top_level.txt
aioelschools-1.0.6.dist-info/RECORD
